ragbits/core/__init__.py
ragbits/core/cli.py
ragbits/core/config.py
ragbits/core/options.py
ragbits/core/py.typed
ragbits/core/types.py
ragbits/core/audit/__init__.py
ragbits/core/audit/metrics/__init__.py
ragbits/core/audit/metrics/base.py
ragbits/core/audit/metrics/logfire.py
ragbits/core/audit/metrics/otel.py
ragbits/core/audit/traces/__init__.py
ragbits/core/audit/traces/base.py
ragbits/core/audit/traces/cli.py
ragbits/core/audit/traces/logfire.py
ragbits/core/audit/traces/otel.py
ragbits/core/embeddings/__init__.py
ragbits/core/embeddings/base.py
ragbits/core/embeddings/exceptions.py
ragbits/core/embeddings/dense/__init__.py
ragbits/core/embeddings/dense/base.py
ragbits/core/embeddings/dense/fastembed.py
ragbits/core/embeddings/dense/litellm.py
ragbits/core/embeddings/dense/local.py
ragbits/core/embeddings/dense/noop.py
ragbits/core/embeddings/dense/vertex_multimodal.py
ragbits/core/embeddings/sparse/__init__.py
ragbits/core/embeddings/sparse/bag_of_tokens.py
ragbits/core/embeddings/sparse/base.py
ragbits/core/embeddings/sparse/fastembed.py
ragbits/core/llms/__init__.py
ragbits/core/llms/base.py
ragbits/core/llms/exceptions.py
ragbits/core/llms/factory.py
ragbits/core/llms/litellm.py
ragbits/core/llms/local.py
ragbits/core/llms/mock.py
ragbits/core/prompt/__init__.py
ragbits/core/prompt/_cli.py
ragbits/core/prompt/base.py
ragbits/core/prompt/discovery.py
ragbits/core/prompt/exceptions.py
ragbits/core/prompt/parsers.py
ragbits/core/prompt/prompt.py
ragbits/core/prompt/promptfoo.py
ragbits/core/sources/__init__.py
ragbits/core/sources/azure.py
ragbits/core/sources/base.py
ragbits/core/sources/exceptions.py
ragbits/core/sources/gcs.py
ragbits/core/sources/git.py
ragbits/core/sources/google_drive.py
ragbits/core/sources/hf.py
ragbits/core/sources/local.py
ragbits/core/sources/s3.py
ragbits/core/sources/web.py
ragbits/core/utils/__init__.py
ragbits/core/utils/_pyproject.py
ragbits/core/utils/config_handling.py
ragbits/core/utils/decorators.py
ragbits_core-1.3.0.dist-info/METADATA
ragbits_core-1.3.0.dist-info/WHEEL
ragbits_core-1.3.0.dist-info/RECORD
